Bubblez/__init__.py
Bubblez/classes/Color.py
Bubblez/classes/Log.py
Bubblez/classes/api/Setup.py
Bubblez/classes/api/receive/Devlog.py
Bubblez/classes/api/receive/Post.py
Bubblez/classes/api/receive/Reply.py
Bubblez/classes/api/receive/User.py
Bubblez/classes/api/send/Devlog.py
Bubblez/classes/api/send/Post.py
Bubblez/classes/api/send/Reply.py
Bubblez/classes/api/send/User.py
Bubblez/classes/socket/events/events.py
Bubblez/classes/socket/receive/Devlog.py
Bubblez/classes/socket/receive/Edit.py
Bubblez/classes/socket/receive/Follower.py
Bubblez/classes/socket/receive/Likes.py
Bubblez/classes/socket/receive/Post.py
Bubblez/classes/socket/receive/Reply.py
Bubblez/classes/socket/receive/User.py
Bubblez/socket/__init__.py
Bubblez/socket/classes.py
Bubblez/socket/core.py
examples/API_examples.py
examples/SOCKET_examples.py
Bubblez.py-0.0.5.5.8.dist-info/LICENSE
Bubblez.py-0.0.5.5.8.dist-info/METADATA
Bubblez.py-0.0.5.5.8.dist-info/WHEEL
Bubblez.py-0.0.5.5.8.dist-info/top_level.txt
Bubblez.py-0.0.5.5.8.dist-info/RECORD
