Metadata-Version: 2.1
Name: Bubblez.py
Version: 0.0.5.5.8
Summary: Api Module for https://bubblez.app/ and websockets
Home-page: UNKNOWN
Author: Mees Meijer (Discord: @MeeSOS#1721)  support@meesinc.nl
License: UNKNOWN
Keywords: python,api,websockets
Platform: UNKNOWN
Classifier: Intended Audience :: Developers
Classifier: Programming Language :: Python :: 3
Classifier: Operating System :: Unix
Classifier: Operating System :: MacOS :: MacOS X
Classifier: Operating System :: Microsoft :: Windows
Requires: wheel
License-File: LICENSE
Requires-Dist: requests
